aiosendspin/__init__.py
aiosendspin/py.typed
aiosendspin/util.py
aiosendspin/client/__init__.py
aiosendspin/client/client.py
aiosendspin/client/listener.py
aiosendspin/client/time_sync.py
aiosendspin/models/__init__.py
aiosendspin/models/artwork.py
aiosendspin/models/controller.py
aiosendspin/models/core.py
aiosendspin/models/metadata.py
aiosendspin/models/player.py
aiosendspin/models/types.py
aiosendspin/models/visualizer.py
aiosendspin/server/__init__.py
aiosendspin/server/client.py
aiosendspin/server/controller.py
aiosendspin/server/events.py
aiosendspin/server/group.py
aiosendspin/server/metadata.py
aiosendspin/server/player.py
aiosendspin/server/server.py
aiosendspin/server/stream.py
aiosendspin/server/visualizer.py
aiosendspin-3.0.1.dist-info/licenses/LICENSE
aiosendspin-3.0.1.dist-info/METADATA
aiosendspin-3.0.1.dist-info/WHEEL
aiosendspin-3.0.1.dist-info/top_level.txt
aiosendspin-3.0.1.dist-info/RECORD
